ne_pretty/__init__.py
ne_pretty/entity_add_context.py
ne_pretty/entity_add_rule_context.py
ne_pretty/entity_cross_do_connect.py
ne_pretty/entity_diff.py
ne_pretty/entity_do_connect.py
ne_pretty/entity_extend_prefix.py
ne_pretty/entity_extend_suffix.py
ne_pretty/entity_remove_contain.py
ne_pretty/entity_remove_dup.py
ne_pretty/entity_remove_eq.py
ne_pretty/entity_remove_prefix.py
ne_pretty/entity_remove_suffix.py
ne_pretty/restore_file.py
ne_pretty/t.py
ne_pretty/test_py.py
ne_pretty/utils.py
ne_pretty-0.0.7.dist-info/METADATA
ne_pretty-0.0.7.dist-info/WHEEL
ne_pretty-0.0.7.dist-info/top_level.txt
ne_pretty-0.0.7.dist-info/RECORD
